{
  "employee": "Ravi Varma",
  "createdAt": "2025-09-25T15:40:02.236888",
  "files": [
    {
      "filename": "Screenshot 2025-09-18 104640.png",
      "type": "prescription",
      "prescriptionNames": [
        "CALPOL",
        "DELCON",
        "LEVOLIN",
        "MEFTAL-P"
      ],
      "billItems": []
    },
    {
      "filename": "Screenshot_14-9-2025_2282_.jpeg",
      "type": "bill",
      "prescriptionNames": [],
      "billItems": [
        {
          "name": "Consultation / Procedure",
          "amount": 500.0
        }
      ]
    }
  ],
  "aggregated": {
    "prescriptions": [
      {
        "names": [
          "CALPOL",
          "DELCON",
          "LEVOLIN",
          "MEFTAL-P"
        ]
      }
    ],
    "bills": [
      {
        "items": [
          {
            "name": "Consultation / Procedure",
            "amount": 500.0
          }
        ]
      }
    ]
  }
}